dvh/__init__.py
dvh/__main__.py
dvh/admin.py
dvh/main.py
dvh/settings.py
dvh/update_sys_path.py
dvh/modules/__init__.py
dvh/modules/default_options.py
dvh/modules/paths.py
dvh/modules/admin/__init__.py
dvh/modules/admin/backup.py
dvh/modules/admin/baseline_plans.py
dvh/modules/admin/database_editor.py
dvh/modules/admin/import_notes.py
dvh/modules/admin/protocol.py
dvh/modules/admin/roi_manager.py
dvh/modules/admin/toxicity.py
dvh/modules/main/__init__.py
dvh/modules/main/categories.py
dvh/modules/main/columns.py
dvh/modules/main/correlation.py
dvh/modules/main/custom_titles.py
dvh/modules/main/data_tables.py
dvh/modules/main/dvhs.py
dvh/modules/main/mlc_analyzer.py
dvh/modules/main/planning_data.py
dvh/modules/main/query.py
dvh/modules/main/rad_bio.py
dvh/modules/main/regression.py
dvh/modules/main/roi_viewer.py
dvh/modules/main/source_listener.py
dvh/modules/main/sources.py
dvh/modules/main/time_series.py
dvh/modules/settings/__init__.py
dvh/modules/settings/custom_options.py
dvh/modules/settings/dicom_directories.py
dvh/modules/settings/sql_config.py
dvh/modules/tools/__init__.py
dvh/modules/tools/auth.py
dvh/modules/tools/get_settings.py
dvh/modules/tools/mlc_analyzer.py
dvh/modules/tools/utilities.py
dvh/modules/tools/io/__init__.py
dvh/modules/tools/io/database/__init__.py
dvh/modules/tools/io/database/analysis_tools.py
dvh/modules/tools/io/database/recalculate.py
dvh/modules/tools/io/database/sql_connector.py
dvh/modules/tools/io/database/sql_to_python.py
dvh/modules/tools/io/database/update.py
dvh/modules/tools/io/database/dicom/__init__.py
dvh/modules/tools/io/database/dicom/importer.py
dvh/modules/tools/io/database/dicom/parser.py
dvh/modules/tools/io/preferences/__init__.py
dvh/modules/tools/io/preferences/import_settings.py
dvh/modules/tools/io/preferences/options.py
dvh/modules/tools/io/preferences/sql.py
dvh/modules/tools/roi/__init__.py
dvh/modules/tools/roi/formatter.py
dvh/modules/tools/roi/geometry.py
dvh/modules/tools/roi/name_manager.py
dvh_analytics-0.5.11.dist-info/LICENSE
dvh_analytics-0.5.11.dist-info/METADATA
dvh_analytics-0.5.11.dist-info/WHEEL
dvh_analytics-0.5.11.dist-info/entry_points.txt
dvh_analytics-0.5.11.dist-info/top_level.txt
dvh_analytics-0.5.11.dist-info/RECORD
